[
    {
        "id": "27197776321752122393569",
        "title": "于深空见证的 - (《恋与深空》4.0版本主题曲)",
        "duration": "04:58",
        "singers": "恋与深空/张韶涵"
    },
    {
        "id": "27224960951752122393569",
        "title": "于深空见证的 (伴奏)",
        "duration": "04:58",
        "singers": "恋与深空/张韶涵"
    },
    {
        "id": "26662788131752122401114",
        "title": "万象遇你 - (《恋与深空》3.0版本主题曲)",
        "duration": "03:45",
        "singers": "恋与深空/吴碧霞"
    },
    {
        "id": "26662788141752122401114",
        "title": "万象遇你 (伴奏)",
        "duration": "03:45",
        "singers": "恋与深空/一棵小葱"
    },
    {
        "id": "26602223781752122408563",
        "title": "深空回响",
        "duration": "03:37",
        "singers": "恋与深空"
    },
    {
        "id": "26602223661752122408563",
        "title": "和你的每一天",
        "duration": "02:32",
        "singers": "恋与深空"
    },
    {
        "id": "26602223731752122408563",
        "title": "遇见你",
        "duration": "02:20",
        "singers": "恋与深空"
    },
    {
        "id": "26602223761752122408563",
        "title": "深空传说",
        "duration": "03:19",
        "singers": "恋与深空"
    },
    {
        "id": "26602223771752122408563",
        "title": "时空引力",
        "duration": "03:36",
        "singers": "恋与深空"
    },
    {
        "id": "26602223741752122408563",
        "title": "第一缕光",
        "duration": "02:10",
        "singers": "恋与深空"
    },
    {
        "id": "26602223641752122408563",
        "title": "奇遇",
        "duration": "02:29",
        "singers": "恋与深空"
    },
    {
        "id": "26602223711752122408563",
        "title": "眸色深处",
        "duration": "02:20",
        "singers": "恋与深空"
    },
    {
        "id": "26602223651752122408563",
        "title": "雾行夜",
        "duration": "02:02",
        "singers": "恋与深空"
    },
    {
        "id": "26602223671752122408563",
        "title": "绮境幻想",
        "duration": "02:03",
        "singers": "恋与深空"
    },
    {
        "id": "26602223701752122408563",
        "title": "昔愿遂心",
        "duration": "02:20",
        "singers": "恋与深空"
    },
    {
        "id": "26602223691752122408563",
        "title": "星航梦旅",
        "duration": "02:22",
        "singers": "恋与深空"
    },
    {
        "id": "26602223681752122408563",
        "title": "深海的祷歌",
        "duration": "02:11",
        "singers": "恋与深空"
    },
    {
        "id": "26602223751752122408563",
        "title": "月下追踪",
        "duration": "02:22",
        "singers": "恋与深空"
    },
    {
        "id": "26602223721752122408563",
        "title": "霜天雪霁",
        "duration": "02:19",
        "singers": "恋与深空"
    },
    {
        "id": "26602201251752122408563",
        "title": "龙谷咏叹",
        "duration": "03:13",
        "singers": "恋与深空"
    },
    {
        "id": "26602201281752122408563",
        "title": "欲揽旖旎色",
        "duration": "03:11",
        "singers": "恋与深空"
    },
    {
        "id": "26602201261752122408563",
        "title": "半透明侵占",
        "duration": "02:33",
        "singers": "恋与深空"
    },
    {
        "id": "26602201241752122408563",
        "title": "双影交叠时",
        "duration": "02:16",
        "singers": "恋与深空"
    },
    {
        "id": "26602201211752122408563",
        "title": "弥望尽头",
        "duration": "01:45",
        "singers": "恋与深空"
    },
    {
        "id": "26602201201752122408563",
        "title": "心潮微澜",
        "duration": "01:10",
        "singers": "恋与深空"
    },
    {
        "id": "26602201231752122408563",
        "title": "无人知晓时",
        "duration": "01:55",
        "singers": "恋与深空"
    },
    {
        "id": "26602201221752122408563",
        "title": "眸光映照处",
        "duration": "01:50",
        "singers": "恋与深空"
    },
    {
        "id": "26602201271752122408563",
        "title": "遵命，饲养官",
        "duration": "02:59",
        "singers": "恋与深空"
    },
    {
        "id": "26602201171752122408563",
        "title": "心动变曲",
        "duration": "01:08",
        "singers": "恋与深空"
    },
    {
        "id": "26602201141752122408563",
        "title": "味蕾突袭",
        "duration": "00:55",
        "singers": "恋与深空"
    },
    {
        "id": "26602201151752122408563",
        "title": "温软怦然",
        "duration": "00:53",
        "singers": "恋与深空"
    },
    {
        "id": "26602201191752122408563",
        "title": "离群者的远航",
        "duration": "01:11",
        "singers": "恋与深空"
    },
    {
        "id": "26602201181752122408563",
        "title": "银瀑奏鸣",
        "duration": "01:10",
        "singers": "恋与深空"
    },
    {
        "id": "26602201161752122408563",
        "title": "临危",
        "duration": "00:55",
        "singers": "恋与深空"
    },
    {
        "id": "26602200871752122408563",
        "title": "皎月下的黑棘",
        "duration": "01:09",
        "singers": "恋与深空"
    },
    {
        "id": "26602200791752122408563",
        "title": "脉脉倾音",
        "duration": "01:05",
        "singers": "恋与深空"
    },
    {
        "id": "26602200811752122408563",
        "title": "专属教学",
        "duration": "00:52",
        "singers": "恋与深空"
    },
    {
        "id": "26602200851752122408563",
        "title": "抵此心上",
        "duration": "01:00",
        "singers": "恋与深空"
    },
    {
        "id": "26602200891752122408563",
        "title": "焰火如誓",
        "duration": "01:21",
        "singers": "恋与深空"
    },
    {
        "id": "26602200781752122408563",
        "title": "煦日私旅",
        "duration": "00:55",
        "singers": "恋与深空"
    },
    {
        "id": "26602200821752122408563",
        "title": "熠熠描摹",
        "duration": "00:53",
        "singers": "恋与深空"
    },
    {
        "id": "26602200801752122408563",
        "title": "长思入画",
        "duration": "01:03",
        "singers": "恋与深空"
    },
    {
        "id": "26602200881752122408563",
        "title": "秘焰沸腾之地",
        "duration": "01:15",
        "singers": "恋与深空"
    },
    {
        "id": "26602200921752122408563",
        "title": "有形之锢",
        "duration": "03:12",
        "singers": "恋与深空"
    },
    {
        "id": "26602200901752122408563",
        "title": "久候狂欢之徒",
        "duration": "02:27",
        "singers": "恋与深空"
    },
    {
        "id": "26602200831752122408563",
        "title": "不设防禁区",
        "duration": "01:05",
        "singers": "恋与深空"
    },
    {
        "id": "26602200841752122408563",
        "title": "炽光淋漓",
        "duration": "01:02",
        "singers": "恋与深空"
    },
    {
        "id": "26602200861752122408563",
        "title": "失落之歌",
        "duration": "01:01",
        "singers": "恋与深空"
    },
    {
        "id": "26602200911752122408563",
        "title": "漫长的等待",
        "duration": "01:57",
        "singers": "恋与深空"
    },
    {
        "id": "26602223531752122408563",
        "title": "精英猎人",
        "duration": "01:31",
        "singers": "恋与深空"
    },
    {
        "id": "26602223591752122408563",
        "title": "夜猎",
        "duration": "02:00",
        "singers": "恋与深空"
    },
    {
        "id": "26602223611752122408563",
        "title": "无尽战意",
        "duration": "03:02",
        "singers": "恋与深空"
    },
    {
        "id": "26602223521752122408563",
        "title": "百炼",
        "duration": "01:21",
        "singers": "恋与深空"
    },
    {
        "id": "26602223571752122408563",
        "title": "宙途",
        "duration": "01:50",
        "singers": "恋与深空"
    },
    {
        "id": "26602223621752122408563",
        "title": "恬梦",
        "duration": "02:32",
        "singers": "恋与深空"
    },
    {
        "id": "26602223491752122408563",
        "title": "太阳雨",
        "duration": "01:04",
        "singers": "恋与深空"
    },
    {
        "id": "26602223481752122408563",
        "title": "一吻",
        "duration": "01:12",
        "singers": "恋与深空"
    },
    {
        "id": "26602223511752122408563",
        "title": "跳跳糖",
        "duration": "01:05",
        "singers": "恋与深空"
    },
    {
        "id": "26602223561752122408563",
        "title": "念念",
        "duration": "01:31",
        "singers": "恋与深空"
    },
    {
        "id": "26602223501752122408563",
        "title": "遥远的时光",
        "duration": "01:34",
        "singers": "恋与深空"
    },
    {
        "id": "26602223551752122408563",
        "title": "谧夜",
        "duration": "01:36",
        "singers": "恋与深空"
    },
    {
        "id": "26602223541752122408563",
        "title": "彷徨之心",
        "duration": "01:47",
        "singers": "恋与深空"
    },
    {
        "id": "26602223581752122408563",
        "title": "诱陷",
        "duration": "02:38",
        "singers": "恋与深空"
    },
    {
        "id": "26602223601752122408563",
        "title": "午后的叶隙",
        "duration": "02:32",
        "singers": "恋与深空"
    },
    {
        "id": "26602200701752122408563",
        "title": "暮色中",
        "duration": "01:51",
        "singers": "恋与深空"
    },
    {
        "id": "26602200681752122408563",
        "title": "浮岚间",
        "duration": "01:31",
        "singers": "恋与深空"
    },
    {
        "id": "26602200721752122408563",
        "title": "别时",
        "duration": "02:19",
        "singers": "恋与深空"
    },
    {
        "id": "26602200671752122408563",
        "title": "临空",
        "duration": "01:34",
        "singers": "恋与深空"
    },
    {
        "id": "26602200691752122408563",
        "title": "局中局",
        "duration": "01:49",
        "singers": "恋与深空"
    },
    {
        "id": "26602200741752122408563",
        "title": "月晕",
        "duration": "02:37",
        "singers": "恋与深空"
    },
    {
        "id": "26602200731752122408563",
        "title": "沉眠",
        "duration": "02:32",
        "singers": "恋与深空"
    },
    {
        "id": "26602200711752122408563",
        "title": "夜空的秘密",
        "duration": "02:31",
        "singers": "恋与深空"
    },
    {
        "id": "26069826831752122445992",
        "title": "交错视界 - (Visions opposées)",
        "duration": "03:11",
        "singers": "恋与深空/Mikelangelo Loconte"
    },
    {
        "id": "26069826901752122445992",
        "title": "交错视界 (伴奏)",
        "duration": "03:11",
        "singers": "恋与深空"
    },
    {
        "id": "21143194321752122472600",
        "title": "恋与深空",
        "duration": "03:28",
        "singers": "恋与深空/Sarah Brightman"
    },
    {
        "id": "21143194971752122472600",
        "title": "恋与深空 (伴奏)",
        "duration": "03:28",
        "singers": "恋与深空"
    }
]